extorch4/__init__.py
extorch4/data_generator.py
extorch4/metrics.py
extorch4/metricsInterface.py
extorch4/torchmodel.py
extorch4/tuner.py
extorch4/test/__init__.py
extorch4/test/test_data_generator.py
extorch4/test/test_linear_sequential.py
extorch4/test/test_sequential_model.py
extorch4/test/test_tuner.py
extorch4-0.0.1.dist-info/LICENSE.txt
extorch4-0.0.1.dist-info/METADATA
extorch4-0.0.1.dist-info/WHEEL
extorch4-0.0.1.dist-info/top_level.txt
extorch4-0.0.1.dist-info/RECORD
