Metadata-Version: 2.1
Name: extorch4
Version: 0.0.1
Summary: torch sequential extension
Home-page: http://pypi.python.org/pypi/extorch2/
Author: denis-spe
Author-email: denisbrian07@gmail.com
License: LICENSE.txt
License-File: LICENSE.txt
Requires-Dist: torchinfo
Requires-Dist: tqdm
